lingvo-0.13.1.dist-info/RECORD
lingvo-0.13.1.dist-info/METADATA
lingvo-0.13.1.dist-info/WHEEL
lingvo-0.13.1.dist-info/top_level.txt
lingvo-0.13.1.dist-info/LICENSE
lingvo/compat.py
lingvo/ipython_kernel.py
lingvo/runners.py
lingvo/model_registry.py
lingvo/datasets.py
lingvo/eager_runners.py
lingvo/model_imports.py
lingvo/executor.py
lingvo/base_trial.py
lingvo/models_test_helper.py
lingvo/__init__.py
lingvo/trainer.py
lingvo/pdb_wrapper.py
lingvo/base_runner.py
lingvo/trainer_utils.py
lingvo/core/base_input_generator.py
lingvo/core/conv_layers_with_time_padding.py
lingvo/core/gshard_builder.py
lingvo/core/adagraft.py
lingvo/core/wpm_encoder.py
lingvo/core/thread_local_utils.py
lingvo/core/tshape.py
lingvo/core/gpipe.py
lingvo/core/routing_config_helper.py
lingvo/core/repeat_layer.py
lingvo/core/model_helper.py
lingvo/core/favor_attention.py
lingvo/core/self_attention_layer.py
lingvo/core/input_policy.py
lingvo/core/optimizer.py
lingvo/core/tpu_embedding_layers_v2.py
lingvo/core/test_trainer_utils.py
lingvo/core/cluster_factory.py
lingvo/core/base_layer.py
lingvo/core/spectrum_augmenter_on_device.py
lingvo/core/pruning_utils.py
lingvo/core/lstm_frnn_layer.py
lingvo/core/ml_perf_tokenizer.py
lingvo/core/schedule.py
lingvo/core/datasource_tfds.py
lingvo/core/builder.py
lingvo/core/insertion.py
lingvo/core/matrix_functions.py
lingvo/core/libhyperparams_proto.so
lingvo/core/tpu_embedding_layers.py
lingvo/core/egdd.py
lingvo/core/reversible_layers.py
lingvo/core/constants.py
lingvo/core/gshard_utils.py
lingvo/core/trainer_test_utils.py
lingvo/core/distillation_task.py
lingvo/core/scatter_update.py
lingvo/core/early_stop.py
lingvo/core/nested_map.py
lingvo/core/graddrop.py
lingvo/core/attention.py
lingvo/core/plot.py
lingvo/core/cluster.py
lingvo/core/conv_layers_builder.py
lingvo/core/lazy_loader.py
lingvo/core/summary_utils.py
lingvo/core/base_decoder.py
lingvo/core/hyperparams.py
lingvo/core/target_sequence_sampler.py
lingvo/core/metrics.py
lingvo/core/test_helper.py
lingvo/core/hyperparams_pb2.py
lingvo/core/gshard_decode.py
lingvo/core/layers_with_attention.py
