Metadata-Version: 2.1
Name: lingvo
Version: 0.13.1
Summary: Lingvo libraries.
Author: Lingvo Authors
Author-email: lingvo-bot@google.com
License: Apache 2.0
Keywords: Machine learning framework
Classifier: Development Status :: 5 - Production/Stable
Classifier: Intended Audience :: Developers
Classifier: Intended Audience :: Education
Classifier: Intended Audience :: Science/Research
Classifier: License :: OSI Approved :: Apache Software License
Classifier: Programming Language :: Python :: 3.8
Classifier: Programming Language :: Python :: 3.9
Classifier: Programming Language :: Python :: 3.10
Classifier: Programming Language :: Python :: 3 :: Only
Classifier: Topic :: Scientific/Engineering
Classifier: Topic :: Scientific/Engineering :: Artificial Intelligence
Classifier: Topic :: Software Development
Classifier: Topic :: Software Development :: Libraries
Classifier: Topic :: Software Development :: Libraries :: Python Modules
Requires-Python: >=3.8,<3.11
License-File: LICENSE
Requires-Dist: attrs
Requires-Dist: apache-beam
Requires-Dist: backports.lzma
Requires-Dist: etils
Requires-Dist: graph-compression-google-research
Requires-Dist: ipykernel
Requires-Dist: jupyter-http-over-ws
Requires-Dist: jupyter
Requires-Dist: matplotlib
Requires-Dist: model-pruning-google-research
Requires-Dist: Pillow ~=10.0.0
Requires-Dist: protobuf
Requires-Dist: scikit-learn
Requires-Dist: sentencepiece
Requires-Dist: sympy
Requires-Dist: tensorflow-datasets
Requires-Dist: tensorflow-hub
Requires-Dist: tensorflow-probability
Requires-Dist: tensorflow-text ~=2.13.0
Requires-Dist: tensorflow ~=2.13.0
